wshuyi_nb2pdf/__init__.py
wshuyi_nb2pdf/__main__.py
wshuyi_nb2pdf/cli.py
wshuyi_nb2pdf/converter.py
wshuyi_nb2pdf-0.1.1.dist-info/METADATA
wshuyi_nb2pdf-0.1.1.dist-info/WHEEL
wshuyi_nb2pdf-0.1.1.dist-info/entry_points.txt
wshuyi_nb2pdf-0.1.1.dist-info/top_level.txt
wshuyi_nb2pdf-0.1.1.dist-info/RECORD
