Metadata-Version: 2.2
Name: wshuyi-nb2pdf
Version: 0.1.1
Summary: 将Jupyter Notebook转换为优化的PDF格式，确保代码完整显示且不被截断
Home-page: https://github.com/yourusername/wshuyi-nb2pdf
Author: WSY
Author-email: wsy@example.com
Classifier: Programming Language :: Python :: 3
Classifier: License :: OSI Approved :: MIT License
Classifier: Operating System :: OS Independent
Requires-Python: >=3.7
Requires-Dist: jupyter
Requires-Dist: nbconvert>=6.0.0
Requires-Dist: playwright>=1.20.0
Dynamic: author
Dynamic: author-email
Dynamic: classifier
Dynamic: description
Dynamic: description-content-type
Dynamic: home-page
Dynamic: requires-dist
Dynamic: requires-python
Dynamic: summary
